b3j0f/__init__.py
b3j0f/annotation/__init__.py
b3j0f/annotation/async.py
b3j0f/annotation/call.py
b3j0f/annotation/check.py
b3j0f/annotation/core.py
b3j0f/annotation/interception.py
b3j0f/annotation/oop.py
b3j0f/annotation/version.py
b3j0f/annotation/test/__init__.py
b3j0f/annotation/test/async.py
b3j0f/annotation/test/call.py
b3j0f/annotation/test/check.py
b3j0f/annotation/test/core.py
b3j0f/annotation/test/interception.py
b3j0f/annotation/test/oop.py
b3j0f.annotation-0.3.6.dist-info/DESCRIPTION.rst
b3j0f.annotation-0.3.6.dist-info/METADATA
b3j0f.annotation-0.3.6.dist-info/RECORD
b3j0f.annotation-0.3.6.dist-info/WHEEL
b3j0f.annotation-0.3.6.dist-info/metadata.json
b3j0f.annotation-0.3.6.dist-info/top_level.txt
