Metadata-Version: 1.1
Name: b3j0f.annotation
Version: 0.3.6
Summary: Reflective annotation library for python
Home-page: https://github.com/b3j0f/annotation
Author: b3j0f
Author-email: jlabejof@yahoo.fr
License: MIT License
Keywords: annotation,decorator,type,check,async,interceptor,oop,call,mixin,transform,curried,retries,deprecated,reflect,reflectivity
Platform: UNKNOWN
Classifier: Development Status :: 4 - Beta
Classifier: License :: OSI Approved :: MIT License
Classifier: Natural Language :: French
Classifier: Operating System :: OS Independent
Classifier: Topic :: Utilities
Classifier: Topic :: Software Development
Classifier: Intended Audience :: Developers
Classifier: Intended Audience :: Science/Research
Classifier: Programming Language :: Python
Classifier: Programming Language :: Python :: 2.6
Classifier: Programming Language :: Python :: 2.7
Classifier: Programming Language :: Python :: 3
Classifier: Programming Language :: Python :: 3.0
Classifier: Programming Language :: Python :: 3.1
Classifier: Programming Language :: Python :: 3.2
Classifier: Programming Language :: Python :: 3.3
Classifier: Programming Language :: Python :: 3.4
Classifier: Programming Language :: Python :: 3.5
Classifier: Programming Language :: Python :: Implementation :: CPython
